adminlogcontrol/__init__.py
adminlogcontrol/asgi.py
adminlogcontrol/settings.py
adminlogcontrol/urls.py
adminlogcontrol/wsgi.py
admintools/__init__.py
admintools/admin.py
admintools/apps.py
admintools/models.py
admintools/signals.py
admintools/tests.py
admintools/views.py
admintools/migrations/__init__.py
django_admin_log_control-1.2.0.dist-info/LICENSE
django_admin_log_control-1.2.0.dist-info/METADATA
django_admin_log_control-1.2.0.dist-info/WHEEL
django_admin_log_control-1.2.0.dist-info/top_level.txt
django_admin_log_control-1.2.0.dist-info/RECORD
