Metadata-Version: 2.1
Name: django-admin-log-control
Version: 1.2.0
Summary: Control your admin-panel changes
Home-page: https://github.com/nkhinatolla/django-admin-logs-control/
Author: Nurbergen
Author-email: nhinatolla@gmail.com
License: MIT
Platform: UNKNOWN
Classifier: Development Status :: 3 - Alpha
Classifier: Programming Language :: Python :: 3
Classifier: License :: OSI Approved :: MIT License
Classifier: Operating System :: OS Independent
License-File: LICENSE
Requires-Dist: psycopg2
Requires-Dist: Django (>=2.2)
Requires-Dist: pyTelegramBotAPI
Requires-Dist: python-dotenv
